show_in_file_manager-1.1.5.data/data/share/man/man1/showinfilemanager.1
showinfm/__init__.py
showinfm/argumentsparse.py
showinfm/constants.py
showinfm/py.typed
showinfm/showinfm.py
showinfm/system/__init__.py
showinfm/system/linux.py
showinfm/system/tools.py
showinfm/system/urivalidate.py
showinfm/system/windows.py
show_in_file_manager-1.1.5.dist-info/LICENSE
show_in_file_manager-1.1.5.dist-info/METADATA
show_in_file_manager-1.1.5.dist-info/WHEEL
show_in_file_manager-1.1.5.dist-info/entry_points.txt
show_in_file_manager-1.1.5.dist-info/top_level.txt
show_in_file_manager-1.1.5.dist-info/RECORD
