Metadata-Version: 2.1
Name: show-in-file-manager
Version: 1.1.5
Summary: Open the system file manager and select files in it
Author-email: Damon Lynch <damonlynch@gmail.com>
Project-URL: Homepage, https://github.com/damonlynch/showinfilemanager
Project-URL: Issues, https://github.com/damonlynch/showinfilemanager/issues
Classifier: Programming Language :: Python :: 3.8
Classifier: Programming Language :: Python :: 3.9
Classifier: Programming Language :: Python :: 3.10
Classifier: Programming Language :: Python :: 3.11
Classifier: Programming Language :: Python :: 3.12
Classifier: License :: OSI Approved :: MIT License
Classifier: Operating System :: MacOS :: MacOS X
Classifier: Operating System :: Microsoft :: Windows :: Windows 10
Classifier: Operating System :: Microsoft :: Windows :: Windows 11
Classifier: Operating System :: POSIX :: Linux
Classifier: Development Status :: 5 - Production/Stable
Classifier: Topic :: Desktop Environment :: File Managers
Classifier: Typing :: Typed
Requires-Python: >=3.8
License-File: LICENSE
Requires-Dist: packaging
Requires-Dist: pyxdg >=0.25 ; platform_system == "Linux"
Requires-Dist: pywin32 >=301 ; platform_system == "Windows"
